neuroindex/__init__.py
neuroindex/core.py
neuroindex/exceptions.py
neuroindex/metrics.py
neuroindex/py.typed
neuroindex-1.0.1.dist-info/licenses/LICENSE
neuroindex-1.0.1.dist-info/METADATA
neuroindex-1.0.1.dist-info/WHEEL
neuroindex-1.0.1.dist-info/top_level.txt
neuroindex-1.0.1.dist-info/RECORD
