Metadata-Version: 2.4
Name: neuroindex
Version: 1.0.1
Summary: Fast vector memory system for AI - FAISS search, SQLite persistence, LRU cache. Community Edition (10K docs, 384-dim).
Author-email: Umeshkumar Pal <umeshkumarpal667@gmail.com>
Maintainer-email: Umeshkumar Pal <umeshkumarpal667@gmail.com>
License: MIT
Project-URL: Homepage, https://github.com/Umeshkumar667/NeuroIndex
Project-URL: Documentation, https://github.com/Umeshkumar667/NeuroIndex#readme
Project-URL: Repository, https://github.com/Umeshkumar667/NeuroIndex
Project-URL: Issues, https://github.com/Umeshkumar667/NeuroIndex/issues
Project-URL: Changelog, https://github.com/Umeshkumar667/NeuroIndex/blob/main/CHANGELOG.md
Project-URL: Upgrade, https://github.com/Umeshkumar667/NeuroIndex/issues
Keywords: vector-database,embeddings,semantic-search,rag,retrieval-augmented-generation,memory,ai,machine-learning,nlp,faiss,chatbot,llm,local-first,vector-search,similarity-search
Classifier: Development Status :: 5 - Production/Stable
Classifier: Intended Audience :: Developers
Classifier: Intended Audience :: Science/Research
Classifier: License :: OSI Approved :: MIT License
Classifier: Operating System :: OS Independent
Classifier: Programming Language :: Python :: 3
Classifier: Programming Language :: Python :: 3.9
Classifier: Programming Language :: Python :: 3.10
Classifier: Programming Language :: Python :: 3.11
Classifier: Programming Language :: Python :: 3.12
Classifier: Topic :: Scientific/Engineering :: Artificial Intelligence
Classifier: Topic :: Database
Classifier: Topic :: Software Development :: Libraries :: Python Modules
Classifier: Typing :: Typed
Requires-Python: >=3.9
License-File: LICENSE
Requires-Dist: numpy>=1.23
Requires-Dist: networkx>=3.0
Requires-Dist: faiss-cpu>=1.7
Provides-Extra: dev
Requires-Dist: pytest>=7.0; extra == "dev"
Requires-Dist: pytest-cov>=4.0; extra == "dev"
Requires-Dist: pytest-xdist>=3.0; extra == "dev"
Requires-Dist: hypothesis>=6.0; extra == "dev"
Requires-Dist: black>=23.0; extra == "dev"
Requires-Dist: isort>=5.0; extra == "dev"
Requires-Dist: mypy>=1.0; extra == "dev"
Requires-Dist: psutil>=5.9; extra == "dev"
Provides-Extra: docs
Requires-Dist: mkdocs>=1.5; extra == "docs"
Requires-Dist: mkdocs-material>=9.0; extra == "docs"
Requires-Dist: mkdocstrings[python]>=0.24; extra == "docs"
Provides-Extra: all
Requires-Dist: neuroindex[dev,docs]; extra == "all"
Dynamic: license-file
